dl_assistant/__init__.py
dl_assistant/image_cnn.py
dl_assistant-0.0.6.dist-info/LICENSE
dl_assistant-0.0.6.dist-info/METADATA
dl_assistant-0.0.6.dist-info/WHEEL
dl_assistant-0.0.6.dist-info/top_level.txt
dl_assistant-0.0.6.dist-info/RECORD
