Metadata-Version: 2.1
Name: dl-assistant
Version: 0.0.6
Summary: A libirary to automate developing keras models
Author: Ayush Agrawal
Author-email: aagrawal963@gmail.com
Keywords: Automated Deep Learning,Model Generation,Neural Network Automation,Deep Learning Automation,AI Model Builder,Neural Architecture Search (NAS),Automated Model Design,Deep Learning Toolkit,Effortless Model Creation,Model Composer,AI Model Automation,Neurogeneration,DL Model Composer,Smart Model Builder,AI Model Generator,Ayush Agrawal,tensorflow,keras
Classifier: Development Status :: 1 - Planning
Classifier: Intended Audience :: Developers
Classifier: Programming Language :: Python :: 3
Classifier: Operating System :: Unix
Classifier: Operating System :: MacOS :: MacOS X
Classifier: Operating System :: Microsoft :: Windows
License-File: LICENSE
Requires-Dist: tensorflow
Requires-Dist: keras
Requires-Dist: notebook
Requires-Dist: tqdm
Requires-Dist: scikit-learn
